statisfy
