Metadata-Version: 2.1
Name: statisfy
Version: 0.0.2
Summary: Get statistics from your favourite social media sites, games and more!
Home-page: https://github.com/aspekts/statisfy.py
Author: Aspekts
Author-email: aspektshelp@gmail.com
License: UNKNOWN
Download-URL: https://github.com/aspekts/statisfy/archive/v_002.tar.gz
Project-URL: Bug Tracker, https://github.com/aspekts/statisfy.py/issues
Keywords: python,stats,statisfy,statistics,api wrapper,analytics
Platform: UNKNOWN
Classifier: Development Status :: 2 - Pre-Alpha
Classifier: Intended Audience :: Developers
Classifier: Programming Language :: Python :: 3
Classifier: Operating System :: Unix
Classifier: Operating System :: MacOS :: MacOS X
Classifier: Operating System :: Microsoft :: Windows
Classifier: License :: OSI Approved :: MIT License
Classifier: Natural Language :: English
